SambathModule.py
SambathModule-1.0.0.dist-info/LICENSE
SambathModule-1.0.0.dist-info/METADATA
SambathModule-1.0.0.dist-info/WHEEL
SambathModule-1.0.0.dist-info/top_level.txt
SambathModule-1.0.0.dist-info/RECORD
