Metadata-Version: 2.1
Name: SambathModule
Version: 1.0.0
Summary: This is for assignment purpose. This package contains weather report and a language translator
Home-page: UNKNOWN
License: UNKNOWN
Platform: UNKNOWN
Classifier: Programming Language :: Python :: 3
Classifier: Programming Language :: Python :: 3.7
Requires-Dist: googletrans
Requires-Dist: feedparser
